[
  {
    "query": "what Are the most frequent threat types in 2022",
    "answer": "Based on description data: (Trend Micro) Since the beginning of 2024, we have been receiving incident response cases from Taiwan. We track this unidentified threat cluster as TIDRONE. Our research reveals that the threat actors have shown significant interest in military-related industry chains, particularly in the manufacturers of drones. Furthermore, telemetry from VirusTotal indicates that the targeted countries are varied; thus, everyone should stay vigilant of this threat. (Supporting evidence from 4 additional sources)",
    "trace_id": "06770dbe-5ed2-4be1-b56d-a3a9712de6bb",
    "model": "fallback",
    "source_count": 5,
    "confidence": 0.7682378649711609,
    "response_id": null,
    "rating": null,
    "relevance": "somewhat_relevant",
    "accuracy": "partially_accurate",
    "completeness": "partial",
    "comments": "Good but one response in related to 2024",
    "corrections": "improve Retrieval . ",
    "feedback_id": "da0fd52a-a597-480e-8d09-c58ca0255fe2",
    "timestamp": "2026-01-31T02:47:56.469089"
  }
]